.installed.cfg
.mr.developer.cfg
CHANGES.rst
CONTRIBUTORS.rst
MANIFEST.in
README.rst
buildout.cfg
setup.py
travis.cfg
src/collective/__init__.py
src/collective/__init__.pyc
src/collective.contact.membrane.egg-info/PKG-INFO
src/collective.contact.membrane.egg-info/SOURCES.txt
src/collective.contact.membrane.egg-info/dependency_links.txt
src/collective.contact.membrane.egg-info/entry_points.txt
src/collective.contact.membrane.egg-info/namespace_packages.txt
src/collective.contact.membrane.egg-info/not-zip-safe
src/collective.contact.membrane.egg-info/pbr.json
src/collective.contact.membrane.egg-info/requires.txt
src/collective.contact.membrane.egg-info/top_level.txt
src/collective/contact/__init__.py
src/collective/contact/__init__.pyc
src/collective/contact/membrane/__init__.py
src/collective/contact/membrane/__init__.pyc
src/collective/contact/membrane/configure.zcml
src/collective/contact/membrane/interfaces.py
src/collective/contact/membrane/interfaces.pyc
src/collective/contact/membrane/setuphandlers.py
src/collective/contact/membrane/setuphandlers.pyc
src/collective/contact/membrane/testing.py
src/collective/contact/membrane/testing.pyc
src/collective/contact/membrane/testing.zcml
src/collective/contact/membrane/behaviors/__init__.py
src/collective/contact/membrane/behaviors/__init__.pyc
src/collective/contact/membrane/behaviors/configure.zcml
src/collective/contact/membrane/behaviors/membranegroup.py
src/collective/contact/membrane/behaviors/membranegroup.pyc
src/collective/contact/membrane/behaviors/personmembraneuser.py
src/collective/contact/membrane/behaviors/personmembraneuser.pyc
src/collective/contact/membrane/content/__init__.py
src/collective/contact/membrane/content/__init__.pyc
src/collective/contact/membrane/content/configure.zcml
src/collective/contact/membrane/locales/collective.contact.membrane.pot
src/collective/contact/membrane/locales/update.sh
src/collective/contact/membrane/locales/fr/LC_MESSAGES/collective.contact.membrane.mo
src/collective/contact/membrane/locales/fr/LC_MESSAGES/collective.contact.membrane.po
src/collective/contact/membrane/profiles/default/collectivecontactmembrane_marker.txt
src/collective/contact/membrane/profiles/default/membrane_tool.xml
src/collective/contact/membrane/profiles/default/metadata.xml
src/collective/contact/membrane/profiles/default/registry.xml
src/collective/contact/membrane/profiles/default/types/organization.xml
src/collective/contact/membrane/profiles/default/types/person.xml
