Metadata-Version: 1.1
Name: collective.contact.membrane
Version: 1.0.2
Summary: Membrane integration for collective.contact content types
Home-page: http://pypi.python.org/pypi/collective.contact.membrane
Author: Cédric Messiant
Author-email: cedricmessiant@ecreall.com
License: GPL
Keywords: contact,membrane
Platform: UNKNOWN
Classifier: Environment :: Web Environment
Classifier: Framework :: Plone
Classifier: Framework :: Plone :: 4.3
Classifier: Programming Language :: Python
Classifier: Programming Language :: Python :: 2.7
